haffmpeg/__init__.py
haffmpeg/camera.py
haffmpeg/core.py
haffmpeg/sensor.py
haffmpeg/timeout.py
haffmpeg/tools.py
ha_ffmpeg-3.2.2.dist-info/LICENSE
ha_ffmpeg-3.2.2.dist-info/METADATA
ha_ffmpeg-3.2.2.dist-info/WHEEL
ha_ffmpeg-3.2.2.dist-info/top_level.txt
ha_ffmpeg-3.2.2.dist-info/RECORD
