Metadata-Version: 2.1
Name: ha-ffmpeg
Version: 3.2.2
Summary: A library that handling with ffmpeg for home-assistant
Home-page: https://github.com/pvizeli/ha-ffmpeg
Download-URL: https://github.com/pvizeli/ha-ffmpeg/tarball/3.2.2
Author: Pascal Vizeli
Author-email: pvizeli@syshack.ch
License: BSD License
Keywords: ffmpeg,homeassistant,wrapper,api
Platform: any
Classifier: Programming Language :: Python
Classifier: Topic :: Software Development :: Libraries :: Python Modules
Classifier: Topic :: Scientific/Engineering :: Atmospheric Science
Classifier: License :: OSI Approved :: BSD License
Classifier: Operating System :: OS Independent
Classifier: Development Status :: 5 - Production/Stable
Classifier: Intended Audience :: Developers
Classifier: Programming Language :: Python :: 3.5
Classifier: Programming Language :: Python :: 3.6
Classifier: Programming Language :: Python :: 3.7
License-File: LICENSE
Requires-Dist: async_timeout
